git_to_prompt/__init__.py
git_to_prompt/__main__.py
git_to_prompt/cli.py
git_to_prompt/formatter.py
git_to_prompt/log.py
git_to_prompt/py.typed
git_to_prompt-0.1.2.dist-info/METADATA
git_to_prompt-0.1.2.dist-info/WHEEL
git_to_prompt-0.1.2.dist-info/entry_points.txt
git_to_prompt-0.1.2.dist-info/licenses/LICENSE
git_to_prompt-0.1.2.dist-info/RECORD
