Metadata-Version: 2.4
Name: git-to-prompt
Version: 0.1.2
Summary: Turn git repository information into LLM prompt context
Project-URL: Homepage, https://github.com/montasaurus/git-to-prompt
Project-URL: Changelog, https://github.com/montasaurus/git-to-prompt/releases
Project-URL: Issues, https://github.com/montasaurus/git-to-prompt/issues
Author: Adam Montgomery
License: Apache-2.0
License-File: LICENSE
Classifier: License :: OSI Approved :: Apache Software License
Requires-Python: >=3.10
Requires-Dist: attrs>=25.1.0
Requires-Dist: cyclopts>=3.9.0
Requires-Dist: gitpython>=3.1.44
